elliottlib/__init__.py
elliottlib/assembly.py
elliottlib/assertion.py
elliottlib/brew.py
elliottlib/build_finder.py
elliottlib/bzutil.py
elliottlib/cincinnati.py
elliottlib/constants.py
elliottlib/cvp.py
elliottlib/dotconfig.py
elliottlib/errata.py
elliottlib/errata_async.py
elliottlib/exceptions.py
elliottlib/exectools.py
elliottlib/gitdata.py
elliottlib/imagecfg.py
elliottlib/logutil.py
elliottlib/metadata.py
elliottlib/model.py
elliottlib/openshiftclient.py
elliottlib/pushd.py
elliottlib/resultsdb.py
elliottlib/rhcos.py
elliottlib/rpm_utils.py
elliottlib/rpmcfg.py
elliottlib/rpmdiff.py
elliottlib/runtime.py
elliottlib/tarball_sources.py
elliottlib/util.py
elliottlib/bug/__init__.py
elliottlib/cli/__init__.py
elliottlib/cli/__main__.py
elliottlib/cli/add_metadata_cli.py
elliottlib/cli/advisory_commons_cli.py
elliottlib/cli/advisory_drop_cli.py
elliottlib/cli/advisory_images_cli.py
elliottlib/cli/advisory_impetus_cli.py
elliottlib/cli/attach_bugs_cli.py
elliottlib/cli/attach_cve_flaws_cli.py
elliottlib/cli/change_state_cli.py
elliottlib/cli/cli_opts.py
elliottlib/cli/common.py
elliottlib/cli/create_cli.py
elliottlib/cli/create_placeholder_cli.py
elliottlib/cli/create_textonly_cli.py
elliottlib/cli/find_bugs_blocker_cli.py
elliottlib/cli/find_bugs_qe_cli.py
elliottlib/cli/find_bugs_sweep_cli.py
elliottlib/cli/find_builds_cli.py
elliottlib/cli/get_golang_versions_cli.py
elliottlib/cli/list_cli.py
elliottlib/cli/puddle_advisories_cli.py
elliottlib/cli/remove_bugs_cli.py
elliottlib/cli/repair_bugs_cli.py
elliottlib/cli/rhcos_cli.py
elliottlib/cli/rpmdiff_cli.py
elliottlib/cli/tag_builds_cli.py
elliottlib/cli/tarball_sources_cli.py
elliottlib/cli/validate_rhsa.py
elliottlib/cli/verify_attached_bugs_cli.py
elliottlib/cli/verify_attached_operators_cli.py
elliottlib/cli/verify_cvp_cli.py
rh_elliott-2.0.14.dist-info/LICENSE
rh_elliott-2.0.14.dist-info/METADATA
rh_elliott-2.0.14.dist-info/WHEEL
rh_elliott-2.0.14.dist-info/entry_points.txt
rh_elliott-2.0.14.dist-info/top_level.txt
rh_elliott-2.0.14.dist-info/RECORD
