Metadata-Version: 2.1
Name: rh-elliott
Version: 2.0.14
Summary: CLI tool for managing and automating Red Hat software releases
Home-page: https://github.com/openshift/elliott
Author: AOS ART Team
Author-email: aos-team-art@redhat.com
License: Apache License, Version 2.0
Classifier: Development Status :: 5 - Production/Stable
Classifier: Programming Language :: Python :: 3
Classifier: Programming Language :: Python :: 3.6
Classifier: Programming Language :: Python :: 3.7
Classifier: Programming Language :: Python :: 3.8
Classifier: Programming Language :: Python :: 3.9
Classifier: Environment :: Console
Classifier: Operating System :: POSIX
Classifier: Operating System :: POSIX :: Linux
Classifier: Operating System :: MacOS
Classifier: License :: OSI Approved :: Apache Software License
Classifier: Intended Audience :: Developers
Classifier: Topic :: Software Development :: Build Tools
Classifier: Natural Language :: English
Requires-Python: >=3.6
License-File: LICENSE
Requires-Dist: aiohttp[speedups] (>=3.6)
Requires-Dist: click (>=8.1.3)
Requires-Dist: errata-tool (>=1.29.0)
Requires-Dist: future
Requires-Dist: koji (>=1.18)
Requires-Dist: semver
Requires-Dist: pygit2 (==1.10.1)
Requires-Dist: python-bugzilla (>=3.2)
Requires-Dist: pyyaml
Requires-Dist: requests
Requires-Dist: requests-kerberos (~=0.14.0)
Requires-Dist: requests-gssapi (~=1.2.3)
Requires-Dist: ruamel.yaml
Requires-Dist: tenacity
Requires-Dist: jira (>=3.4.1)
Requires-Dist: setuptools-scm
Requires-Dist: setuptools (>=65.5.1)
